{
  "Name": "服务端命令2",
  "Enabled": true,
  "Triggers": [
    {
      "$type": "Forguncy.ServerCommands.Models.PostRequestTrigger, ServerDesignerCommon",
      "Permission": {
        "PermissionData": {
          "$type": "Forguncy.RbacPermission.Core.Impl.ServerCommand.ServerCommandPermissionData, Forguncy.RbacPermission.Core",
          "permissionResource": {
            "$type": "Forguncy.RbacPermission.Core.Impl.ServerCommand.ServerCommandPermissionResource, Forguncy.RbacPermission.Core"
          },
          "permissionBindings": [
            {
              "$type": "Forguncy.RbacPermission.Core.Impl.ServerCommand.ServerCommandPermissionBinding, Forguncy.RbacPermission.Core",
              "roleNames": [
                "FGC_LoginUser"
              ]
            }
          ]
        }
      }
    }
  ]
}